netatmo_thermostat/__init__.py
netatmo_thermostat/_modidx.py
netatmo_thermostat/core.py
netatmo_thermostat/solar.py
netatmo_thermostat-0.0.4.dist-info/licenses/LICENSE
netatmo_thermostat-0.0.4.dist-info/METADATA
netatmo_thermostat-0.0.4.dist-info/WHEEL
netatmo_thermostat-0.0.4.dist-info/entry_points.txt
netatmo_thermostat-0.0.4.dist-info/top_level.txt
netatmo_thermostat-0.0.4.dist-info/RECORD
