Metadata-Version: 2.4
Name: netatmo-thermostat
Version: 0.0.4
Summary: A simple Python SDK for the Netatmo Energy API (thermostats).
Home-page: https://github.com/kafkasl/netatmo-thermostat
Author: Pol Alvarez
Author-email: pol.avms@gmail.com
License: Apache Software License 2.0
Keywords: nbdev jupyter notebook python
Classifier: Development Status :: 4 - Beta
Classifier: Intended Audience :: Developers
Classifier: Natural Language :: English
Classifier: Programming Language :: Python :: 3.9
Classifier: Programming Language :: Python :: 3.10
Classifier: Programming Language :: Python :: 3.11
Classifier: Programming Language :: Python :: 3.12
Classifier: License :: OSI Approved :: Apache Software License
Requires-Python: >=3.9
License-File: LICENSE
Requires-Dist: fastcore
Requires-Dist: httpx
Requires-Dist: python-fasthtml
Requires-Dist: monsterui
Requires-Dist: python-dotenv
Provides-Extra: dev
Requires-Dist: matplotlib; extra == "dev"
Requires-Dist: nbdev; extra == "dev"
Requires-Dist: jupyter; extra == "dev"
Dynamic: author
Dynamic: author-email
Dynamic: classifier
Dynamic: description
Dynamic: description-content-type
Dynamic: home-page
Dynamic: keywords
Dynamic: license
Dynamic: license-file
Dynamic: provides-extra
Dynamic: requires-dist
Dynamic: requires-python
Dynamic: summary
